guang_toolkit/__init__.py
guang_toolkit/amap.py
guang_toolkit/basic.py
guang_toolkit/func.py
guang_toolkit/geohash.py
guang_toolkit/logger.py
guang_toolkit/mail.py
guang_toolkit/new_mysql.py
guang_toolkit/new_pickle.py
guang_toolkit/new_redis.py
guang_toolkit/plot.py
guang_toolkit/s3.py
guang_toolkit/weather.py
guang_toolkit/configs/china_weather.ini
guang_toolkit/configs/city_code - 副本.ini
guang_toolkit/configs/city_code.ini
guang_toolkit/configs/city_name.ini
guang_toolkit/configs/crawler.ini
guang_toolkit/configs/last_data.json
guang_toolkit/configs/settings.txt
guang_toolkit/static/image001.png
guang_toolkit/static/signature.html
guang_toolkit-3.0.13.dist-info/LICENSE.txt
guang_toolkit-3.0.13.dist-info/METADATA
guang_toolkit-3.0.13.dist-info/WHEEL
guang_toolkit-3.0.13.dist-info/top_level.txt
guang_toolkit-3.0.13.dist-info/RECORD
