Metadata-Version: 2.1
Name: guang-toolkit
Version: 3.0.13
Summary: python toolkit
Home-page: https://github.com/uncleguanghui/guang_toolkit
Author: guanghui.zhang
Author-email: 415558663@qq.com
License: MIT
Keywords: toolkit,mail,geohash,mysql,pickle,s3,weather,china,amap,crawler
Platform: UNKNOWN
Classifier: Development Status :: 3 - Alpha
Classifier: Environment :: MacOS X
Classifier: License :: OSI Approved :: MIT License
Classifier: Natural Language :: Chinese (Simplified)
Classifier: Operating System :: MacOS
Classifier: Operating System :: POSIX :: Linux
Classifier: Programming Language :: Python :: 3 :: Only
Requires-Python: >=3
Requires-Dist: pandas (>=0.24.2)
Requires-Dist: openpyxl (>=2.5.12)
Requires-Dist: numpy (>=1.16.3)
Requires-Dist: geopy (>=1.14.0)
Requires-Dist: urllib3 (>=1.21.1)
Requires-Dist: jinja2 (>=2.10.1)
Requires-Dist: pymysql (>=0.9.3)
Requires-Dist: redis (>=3.2.1)
Requires-Dist: SQLAlchemy (>=1.3.3)
Requires-Dist: requests (>=2.19.1)
Requires-Dist: cryptography (>=2.6.1)
Requires-Dist: python-dateutil (>=2.6)
Requires-Dist: xlrd (>=1.2.0)
Requires-Dist: pathlib (>=1.0.1)
Requires-Dist: shapely (>=1.6.4.post2)
Requires-Dist: flake8 (>=3.7.7)
Requires-Dist: mysql-connector-python (>=8.0.16)
Requires-Dist: matplotlib (>=3.0.3)
Requires-Dist: boto3 (>=1.9.137)
Requires-Dist: bs4 (>=0.0.1)
Requires-Dist: pypinyin (>=0.36.0)
Requires-Dist: pyarrow (>=0.16.0)
